gitlite/__init__.py
gitlite/add.py
gitlite/branch.py
gitlite/checkout.py
gitlite/commit.py
gitlite/error.py
gitlite/init.py
gitlite/log.py
gitlite/main.py
gitlite/status.py
gitlite/bin/CommitObject.py
gitlite/bin/FileType.py
gitlite/bin/TreeItem.py
gitlite/bin/__init__.py
gitlite/bin/utils.py
gitlite-0.3.5.dist-info/METADATA
gitlite-0.3.5.dist-info/WHEEL
gitlite-0.3.5.dist-info/entry_points.txt
gitlite-0.3.5.dist-info/top_level.txt
gitlite-0.3.5.dist-info/RECORD
