Metadata-Version: 2.4
Name: gitlite
Version: 0.3.5
Summary: A lightweight version of Git-like local Version Control System
Requires-Dist: colorama
Dynamic: description
Dynamic: description-content-type
Dynamic: requires-dist
Dynamic: summary
